README.md
setup.cfg
setup.py
ebayoauth/__init__.py
ebayoauth.egg-info/PKG-INFO
ebayoauth.egg-info/SOURCES.txt
ebayoauth.egg-info/dependency_links.txt
ebayoauth.egg-info/top_level.txt
ebayoauth/oauthclient/__init__.py
ebayoauth/oauthclient/credentialutil.py
ebayoauth/oauthclient/oauth2api.py
ebayoauth/oauthclient/model/__init__.py
ebayoauth/oauthclient/model/model.py
ebayoauth/oauthclient/model/util.py