Metadata-Version: 1.1
Name: ebayoauth
Version: 0.0.1
Summary: eBay OAuth Client
Home-page: https://github.com/aissa-aouli/ebay-oauth-python-client.git
Author: UNKNOWN
Author-email: UNKNOWN
License: UNKNOWN
Download-URL: https://github.com/aissa-aouli/ebay-oauth-python-client/archive/refs/tags/0.0.1.tar.gz
Keywords: ebay,oauth,api
Platform: UNKNOWN
